setup.py
./bright_fabric/__init__.py
./bright_fabric/fab.py
./bright_fabric/fabfile.py
./bright_fabric/tasks.py
./bright_fabric/util.py
./tests/__init__.py
./tests/test_tasks.py
./tests/test_util.py
./tests/util.py
bright_fabric.egg-info/PKG-INFO
bright_fabric.egg-info/SOURCES.txt
bright_fabric.egg-info/dependency_links.txt
bright_fabric.egg-info/requires.txt
bright_fabric.egg-info/top_level.txt