Metadata-Version: 1.0
Name: bright-fabric
Version: 0.1.0
Summary: Bright Interactive's Fabric Utilities
Home-page: http://github.com/brightinteractive/bright-fabric/
Author: Bright Interactive
Author-email: francis@bright-interactive.co.uk
License: BSD
Platform: UNKNOWN
